event_types/__init__.py
godjigame_event_schemas-1.10.0.dist-info/METADATA
godjigame_event_schemas-1.10.0.dist-info/WHEEL
godjigame_event_schemas-1.10.0.dist-info/top_level.txt
godjigame_event_schemas-1.10.0.dist-info/RECORD
