Metadata-Version: 2.4
Name: godjigame-event-schemas
Version: 1.10.0
Summary: Avro-based event schemas for TypeScript and Python services
Home-page: https://github.com/goodgameteamit/event-schemas
Author: Godji Game
Author-email: Godji Game <team@goodgameteamit.com>
License: MIT
Project-URL: Homepage, https://github.com/goodgameteamit/event-schemas
Project-URL: Bug Reports, https://github.com/goodgameteamit/event-schemas/issues
Project-URL: Source, https://github.com/goodgameteamit/event-schemas
Project-URL: Documentation, https://github.com/goodgameteamit/event-schemas#readme
Keywords: avro,schemas,events,typescript,kafka,event-driven
Classifier: Development Status :: 4 - Beta
Classifier: Intended Audience :: Developers
Classifier: License :: OSI Approved :: MIT License
Classifier: Programming Language :: Python :: 3
Classifier: Programming Language :: Python :: 3.8
Classifier: Programming Language :: Python :: 3.9
Classifier: Programming Language :: Python :: 3.10
Classifier: Programming Language :: Python :: 3.11
Classifier: Programming Language :: Python :: 3.12
Classifier: Topic :: Software Development :: Libraries :: Python Modules
Classifier: Topic :: System :: Distributed Computing
Classifier: Topic :: Software Development :: Code Generators
Requires-Python: >=3.8
Requires-Dist: avro-python3>=1.10.0
Provides-Extra: dev
Requires-Dist: pytest>=7.0.0; extra == "dev"
Requires-Dist: pytest-cov>=4.0.0; extra == "dev"
Requires-Dist: black>=22.0.0; extra == "dev"
Requires-Dist: flake8>=5.0.0; extra == "dev"
Requires-Dist: mypy>=1.0.0; extra == "dev"
Dynamic: author
Dynamic: home-page
Dynamic: requires-python
